vcg/__init__.py
vcg/_version.py
vcg/config.py
vcg/host_specific.py
vcg/notifier.py
vcg/sleeper.py
vcg/tools.py
vcg-1.3.0.dist-info/LICENSE
vcg-1.3.0.dist-info/METADATA
vcg-1.3.0.dist-info/WHEEL
vcg-1.3.0.dist-info/top_level.txt
vcg-1.3.0.dist-info/RECORD
